en_audio2text/__init__.py
en_audio2text/aud2text.py
en_audio2text/text_rules.py
en_audio2text_soumyade-0.0.1.2.dist-info/LICENSE
en_audio2text_soumyade-0.0.1.2.dist-info/METADATA
en_audio2text_soumyade-0.0.1.2.dist-info/WHEEL
en_audio2text_soumyade-0.0.1.2.dist-info/top_level.txt
en_audio2text_soumyade-0.0.1.2.dist-info/RECORD
