Metadata-Version: 2.1
Name: en-audio2text-soumyade
Version: 0.0.1.2
Summary: small wrapper around speech recognition package
Home-page: https://github.com/cssoumyade/en_audio2text
Author: Soumya De
Author-email: cs.soumyade@gmail.com
License: UNKNOWN
Project-URL: Bug Tracker, https://github.com/cssoumyade/en_audio2text/issues
Platform: UNKNOWN
Classifier: Development Status :: 2 - Pre-Alpha
Classifier: Intended Audience :: Other Audience
Classifier: Topic :: Education :: Testing
Classifier: Programming Language :: Python :: 3
Classifier: License :: OSI Approved :: MIT License
Requires-Python: >=3.6
